LordTemplate/__init__.py
LordTemplate/custom_importer.py
LordTemplate/filters.py
LordTemplate/importer.py
LordTemplate/jinja_env.py
LordTemplate/table.py
LordTemplate-2023.5.13.1.dist-info/METADATA
LordTemplate-2023.5.13.1.dist-info/WHEEL
LordTemplate-2023.5.13.1.dist-info/top_level.txt
LordTemplate-2023.5.13.1.dist-info/RECORD
