Metadata-Version: 2.1
Name: LordTemplate
Version: 2023.5.13.1
Summary: My Template Lib for Jinja-2
Author-email: lordbex <lordibex@protonmail.com>
Maintainer-email: lordbex <lordibex@protonmail.com>
Project-URL: homepage, https://git.lordbex.xyz/PipModule/LordTemplate.git
Project-URL: repository, https://git.lordbex.xyz/PipModule/LordTemplate.git
Requires-Python: >=3.10
Requires-Dist: regex
Requires-Dist: Jinja2 (~=3.1.2)
Requires-Dist: art (==5.8)
Requires-Dist: pyfiglet (~=0.8.post1)
Requires-Dist: PyYAML (~=6.0)
Requires-Dist: python-dateutil
Requires-Dist: LordPath
Requires-Dist: LordUtils
